skutil/__init__.py
skutil/_version.py
skutil/metrics.py
skutil/version.info
skutil/calibration/__init__.py
skutil/calibration/calib_clf.py
skutil/calibration/calib_clf_cv.py
skutil/estimators/__init__.py
skutil/estimators/classifier_map.py
skutil/estimators/col_ignore_clf.py
skutil/estimators/regressor_map.py
skutil/model_selection/__init__.py
skutil/model_selection/search.py
skutil/preprocessing/__init__.py
skutil/preprocessing/scale.py
skutil-0.0.19.dist-info/licenses/LICENSE
skutil-0.0.19.dist-info/METADATA
skutil-0.0.19.dist-info/WHEEL
skutil-0.0.19.dist-info/top_level.txt
skutil-0.0.19.dist-info/RECORD
