Metadata-Version: 2.4
Name: skutil
Version: 0.0.19
Summary: Utilities for scikit-learn.
Author-email: Shay Palachy Affek <shay.palachy@gmail.com>
License: MIT License
Project-URL: Source, https://github.com/shaypal5/skutil
Keywords: data science,machine learning,python,scikit-learn,sklearn,utilities,utils
Classifier: Development Status :: 4 - Beta
Classifier: Intended Audience :: Developers
Classifier: License :: OSI Approved :: MIT License
Classifier: Programming Language :: Python
Classifier: Programming Language :: Python :: 3 :: Only
Classifier: Programming Language :: Python :: 3.9
Classifier: Programming Language :: Python :: 3.10
Classifier: Programming Language :: Python :: 3.11
Classifier: Programming Language :: Python :: 3.12
Classifier: Programming Language :: Python :: 3.13
Classifier: Topic :: Other/Nonlisted Topic
Classifier: Topic :: Software Development :: Libraries
Classifier: Topic :: Software Development :: Libraries :: Python Modules
Classifier: Topic :: Utilities
License-File: LICENSE
Requires-Dist: decore
Requires-Dist: numpy
Dynamic: license-file
